{
  "id" : "https://NotDMIT.github.io/Delft/manifests/collection.json",
  "label" : {
    "en" : [ "All manifests loaded in NotDMIT/Delft project" ]
  },
  "type" : "Collection",
  "@context" : "http://iiif.io/api/presentation/3/context.json",
  "items" : [ {
    "id" : "https://NotDMIT.github.io/Delft/manifests/01_manifest.json",
    "label" : {
      "en" : [ "Blank Manifest" ]
    },
    "type" : "Manifest"
  }, {
    "id" : "https://NotDMIT.github.io/Delft/manifests/02_manifest.json",
    "label" : {
      "en" : [ "Blank Manifest" ]
    },
    "type" : "Manifest"
  }, {
    "id" : "https://NotDMIT.github.io/Delft/manifests/https://images.historicnewengland.org/iiif/3/30675/info.json",
    "label" : null,
    "type" : "ImageService3"
  } ]
}